[
  {
    "market_hash_name": "Souvenir MP7 | Orange Peel (Well-Worn)",
    "prev_price": 1.85,
    "curr_price": 233.86,
    "pct_change": 12541.08,
    "volume": 1
  },
  {
    "market_hash_name": "Souvenir Desert Eagle | Urban DDPAT (Well-Worn)",
    "prev_price": 0.91,
    "curr_price": 26.77,
    "pct_change": 2841.76,
    "volume": 2
  },
  {
    "market_hash_name": "Souvenir Dual Berettas | Drift Wood (Well-Worn)",
    "prev_price": 0.06,
    "curr_price": 1.08,
    "pct_change": 1700.0,
    "volume": 1
  },
  {
    "market_hash_name": "XM1014 | Blue Tire (Factory New)",
    "prev_price": 2.91,
    "curr_price": 30.69,
    "pct_change": 954.64,
    "volume": 2
  },
  {
    "market_hash_name": "Souvenir Galil AR | Hunting Blind (Well-Worn)",
    "prev_price": 2.31,
    "curr_price": 23.39,
    "pct_change": 912.55,
    "volume": 1
  },
  {
    "market_hash_name": "MP9 | Dizzy (Factory New)",
    "prev_price": 0.07,
    "curr_price": 0.5,
    "pct_change": 614.29,
    "volume": 13
  },
  {
    "market_hash_name": "\u2605 Survival Knife | Case Hardened (Well-Worn)",
    "prev_price": 102.82,
    "curr_price": 605.8,
    "pct_change": 489.18,
    "volume": 2
  },
  {
    "market_hash_name": "Sticker | magixx (Holo, Champion) | Shanghai 2024",
    "prev_price": 0.37,
    "curr_price": 1.98,
    "pct_change": 435.14,
    "volume": 1
  },
  {
    "market_hash_name": "Souvenir AK-47 | Safari Mesh (Field-Tested)",
    "prev_price": 44.67,
    "curr_price": 211.74,
    "pct_change": 374.01,
    "volume": 2
  },
  {
    "market_hash_name": "\u2605 Butterfly Knife | Gamma Doppler (Factory New)",
    "prev_price": 2314.03,
    "curr_price": 10320.87,
    "pct_change": 346.01,
    "volume": 1
  },
  {
    "market_hash_name": "\u2605 Bayonet | Gamma Doppler (Factory New)",
    "prev_price": 496.48,
    "curr_price": 1985.03,
    "pct_change": 299.82,
    "volume": 1
  },
  {
    "market_hash_name": "StatTrak\u2122 AK-47 | The Outsiders (Factory New)",
    "prev_price": 124.36,
    "curr_price": 458.2,
    "pct_change": 268.45,
    "volume": 2
  },
  {
    "market_hash_name": "Souvenir Galil AR | Cerberus (Field-Tested)",
    "prev_price": 96.95,
    "curr_price": 325.43,
    "pct_change": 235.67,
    "volume": 2
  },
  {
    "market_hash_name": "Souvenir P250 | Nuclear Threat (Field-Tested)",
    "prev_price": 103.27,
    "curr_price": 328.31,
    "pct_change": 217.91,
    "volume": 1
  },
  {
    "market_hash_name": "Souvenir XM1014 | Blue Steel (Field-Tested)",
    "prev_price": 55.9,
    "curr_price": 175.4,
    "pct_change": 213.77,
    "volume": 1
  },
  {
    "market_hash_name": "Sticker | EmiliaQAQ (Gold) | Copenhagen 2024",
    "prev_price": 8.41,
    "curr_price": 25.26,
    "pct_change": 200.36,
    "volume": 3
  },
  {
    "market_hash_name": "Souvenir MP5-SD | Dirt Drop (Battle-Scarred)",
    "prev_price": 0.04,
    "curr_price": 0.12,
    "pct_change": 200.0,
    "volume": 2
  },
  {
    "market_hash_name": "Souvenir P90 | Wash me (Battle-Scarred)",
    "prev_price": 0.04,
    "curr_price": 0.12,
    "pct_change": 200.0,
    "volume": 2
  },
  {
    "market_hash_name": "Desert Eagle | Urban Rubble (Factory New)",
    "prev_price": 1.61,
    "curr_price": 4.67,
    "pct_change": 190.06,
    "volume": 23
  },
  {
    "market_hash_name": "Sticker | KOI (Gold) | Copenhagen 2024",
    "prev_price": 4.81,
    "curr_price": 13.26,
    "pct_change": 175.68,
    "volume": 1
  }
]